gotoh/__init__.py
gotoh/gotoh.c
gotoh/gotoh.pyx
gotoh-0.1.7.dist-info/LICENSE
gotoh-0.1.7.dist-info/METADATA
gotoh-0.1.7.dist-info/WHEEL
gotoh-0.1.7.dist-info/RECORD
